qcloud_sdk/__init__.py
qcloud_sdk/api.py
qcloud_sdk/config.py
qcloud_sdk/exceptions.py
qcloud_sdk/settings.toml
qcloud_sdk/base/__init__.py
qcloud_sdk/base/client.py
qcloud_sdk/base/sign.py
qcloud_sdk/cam/__init__.py
qcloud_sdk/cls/__init__.py
qcloud_sdk/cls/api.py
qcloud_sdk/cos/__init__.py
qcloud_sdk/cos/client.py
qcloud_sdk/cos/models.py
qcloud_sdk/cos/sign.py
qcloud_sdk/cos/utils.py
qcloud_sdk/cos/api/__init__.py
qcloud_sdk/cos/api/base.py
qcloud_sdk/cos/api/bucket.py
qcloud_sdk/cos/api/object.py
qcloud_sdk/cos/api/service.py
qcloud_sdk/eb/__init__.py
qcloud_sdk/eb/api.py
qcloud_sdk/iotcloud/__init__.py
qcloud_sdk/iotcloud/api.py
qcloud_sdk/models/__init__.py
qcloud_sdk/models/cloud_resources.py
qcloud_sdk/models/event_bus.py
qcloud_sdk/models/object_storage.py
qcloud_sdk/models/request.py
qcloud_sdk/models/response.py
qcloud_sdk/scf/__init__.py
qcloud_sdk/scf/models.py
qcloud_sdk/scf/settings.toml
qcloud_sdk/scf/api/__init__.py
qcloud_sdk/scf/api/base.py
qcloud_sdk/scf/api/functions.py
qcloud_sdk/scf/api/triggers.py
qcloud_sdk/sms/__init__.py
qcloud_sdk/sms/api.py
qcloud_sdk/tmt/__init__.py
qcloud_sdk/tmt/api.py
qcloud_sdk/utils/__init__.py
qcloud_sdk/utils/collections.py
qcloud_sdk/utils/const.py
qcloud_sdk_py-0.5.0.dist-info/METADATA
qcloud_sdk_py-0.5.0.dist-info/WHEEL
qcloud_sdk_py-0.5.0.dist-info/top_level.txt
qcloud_sdk_py-0.5.0.dist-info/RECORD
