Metadata-Version: 2.1
Name: qcloud-sdk-py
Version: 0.5.0
Summary: Python SDK for TencentCloud
Author-email: "QuantTide Inc." <opensource@quanttide.com>
Classifier: Programming Language :: Python :: 3
Requires-Python: >=3.7
Requires-Dist: requests
Requires-Dist: dynaconf (>=3.0.0)
Requires-Dist: Jinja2
Requires-Dist: cloudevents
Requires-Dist: xmltodict
Requires-Dist: tqdm
Requires-Dist: crcmod
